OTTools/LinearProgramming.py
OTTools/__init__.py
OTTools/transportationProblem.py
ottools-0.1.2.dist-info/licenses/LICENSE
ottools-0.1.2.dist-info/METADATA
ottools-0.1.2.dist-info/WHEEL
ottools-0.1.2.dist-info/top_level.txt
ottools-0.1.2.dist-info/RECORD
