Metadata-Version: 2.4
Name: OTTools
Version: 0.1.2
Summary: A Python package for Linear Programming and Transportation Problems
Home-page: https://github.com/Strangehumaan/OT
Author: Mohammad Saad Nathani,Pranav Mundhra
Author-email: saadnathani2005@gmail.com,pranavmundhara2005@gmail.com
Classifier: Programming Language :: Python :: 3
Classifier: License :: OSI Approved :: MIT License
Requires-Python: >=3.6
License-File: LICENSE
Requires-Dist: numpy
Requires-Dist: pandas
Requires-Dist: plotly
Requires-Dist: scipy
Dynamic: author
Dynamic: author-email
Dynamic: classifier
Dynamic: description
Dynamic: description-content-type
Dynamic: home-page
Dynamic: license-file
Dynamic: requires-dist
Dynamic: requires-python
Dynamic: summary
